gptrim/__init__.py
gptrim/gptrim.py
gptrim-0.1.5.dist-info/LICENSE
gptrim-0.1.5.dist-info/METADATA
gptrim-0.1.5.dist-info/WHEEL
gptrim-0.1.5.dist-info/top_level.txt
gptrim-0.1.5.dist-info/RECORD
