Metadata-Version: 2.1
Name: gptrim
Version: 0.1.5
Summary: Reduce the size of GPT inputs by 40-60% without losing most of the information.
Home-page: https://github.com/vlad-ds/gptrim
Author: Vlad Gheorghe
Author-email: vlad.datapro@gmail.com
Classifier: Development Status :: 3 - Alpha
Classifier: Intended Audience :: Developers
Classifier: License :: OSI Approved :: MIT License
Classifier: Programming Language :: Python :: 3
Classifier: Programming Language :: Python :: 3.8
Classifier: Programming Language :: Python :: 3.9
License-File: LICENSE
Requires-Dist: nltk (==3.8.1)
